docker_load_graph/__init__.py
docker_load_graph/__main__.py
docker_load_graph/docker_helper.py
docker_load_graph/plotting.py
docker_load_graph-1.0.2.dist-info/LICENSE
docker_load_graph-1.0.2.dist-info/METADATA
docker_load_graph-1.0.2.dist-info/WHEEL
docker_load_graph-1.0.2.dist-info/entry_points.txt
docker_load_graph-1.0.2.dist-info/top_level.txt
docker_load_graph-1.0.2.dist-info/RECORD
