Metadata-Version: 2.1
Name: docker-load-graph
Version: 1.0.2
Summary: A simple CLI graph for visualizing load on docker containers
Home-page: https://github.com/cjmcgraw/docker-load-graph
Author: Carl McGraw
Author-email: c@rlmcgraw.io
License: MIT License
Platform: UNKNOWN
License-File: LICENSE
Requires-Dist: python-version (>='3.7')
Requires-Dist: plotext (==3.1.2)
Requires-Dist: pandas (>=1.3.2)
Requires-Dist: numpy (>=1.21.2)
Requires-Dist: docker (>=5.0.0)
